xoscar-0.9.3.dist-info/RECORD
xoscar-0.9.3.dist-info/WHEEL
xoscar-0.9.3.dist-info/top_level.txt
xoscar-0.9.3.dist-info/METADATA
xoscar/_utils.pyx
xoscar/backend.py
xoscar/core.pxd
xoscar/_version.py
xoscar/context.pxd
xoscar/batch.py
xoscar/nvutils.py
xoscar/constants.py
xoscar/__init__.py
xoscar/api.py
xoscar/core.cpython-39-darwin.so
xoscar/utils.py
xoscar/debug.py
xoscar/libcpp.pxd
xoscar/context.pyx
xoscar/errors.py
xoscar/_utils.cpython-39-darwin.so
xoscar/core.pyx
xoscar/driver.py
xoscar/profiling.py
xoscar/_utils.pxd
xoscar/context.cpython-39-darwin.so
xoscar/metrics/__init__.py
xoscar/metrics/api.py
xoscar/metrics/backends/__init__.py
xoscar/metrics/backends/metric.py
xoscar/metrics/backends/prometheus/__init__.py
xoscar/metrics/backends/prometheus/prometheus_metric.py
xoscar/metrics/backends/console/console_metric.py
xoscar/metrics/backends/console/__init__.py
xoscar/collective/xoscar_pygloo.cpython-39-darwin.so
xoscar/collective/__init__.py
xoscar/collective/core.py
xoscar/collective/common.py
xoscar/collective/utils.py
xoscar/collective/process_group.py
xoscar/collective/xoscar_pygloo.pyi
xoscar/collective/backend/nccl_backend.py
xoscar/collective/backend/__init__.py
xoscar/serialization/exception.py
xoscar/serialization/pyfury.py
xoscar/serialization/core.pxd
xoscar/serialization/core.pyi
xoscar/serialization/__init__.py
xoscar/serialization/numpy.py
xoscar/serialization/core.cpython-39-darwin.so
xoscar/serialization/cuda.py
xoscar/serialization/scipy.py
xoscar/serialization/aio.py
xoscar/serialization/core.pyx
xoscar/serialization/torch.py
xoscar/serialization/mlx.py
xoscar/backends/message.cpython-39-darwin.so
xoscar/backends/config.py
xoscar/backends/message.pyi
xoscar/backends/allocate_strategy.py
xoscar/backends/__init__.py
xoscar/backends/core.py
xoscar/backends/context.py
xoscar/backends/router.py
xoscar/backends/message.pyx
xoscar/backends/pool.py
xoscar/backends/indigen/backend.py
xoscar/backends/indigen/shared_memory.py
xoscar/backends/indigen/__init__.py
xoscar/backends/indigen/fate_sharing.py
