Metadata-Version: 2.4
Name: xoscar
Version: 0.9.3
Summary: Python actor framework for heterogeneous computing.
Home-page: http://github.com/xorbitsai/xoscar
Author: Qin Xuye
Author-email: qinxuye@xprobe.io
Maintainer: Qin Xuye
Maintainer-email: qinxuye@xprobe.io
License: Apache License 2.0
Classifier: Operating System :: OS Independent
Classifier: Programming Language :: Python
Classifier: Programming Language :: Python :: 3
Classifier: Programming Language :: Python :: 3.9
Classifier: Programming Language :: Python :: 3.10
Classifier: Programming Language :: Python :: 3.11
Classifier: Programming Language :: Python :: 3.12
Classifier: Programming Language :: Python :: 3.13
Classifier: Programming Language :: Python :: Implementation :: CPython
Classifier: Topic :: Software Development :: Libraries
Requires-Dist: numpy>=1.14.0
Requires-Dist: pandas>=1.0.0
Requires-Dist: scipy<1.17.0,>=1.0.0; sys_platform == "linux" and python_version >= "3.11" and python_version < "3.14"
Requires-Dist: scipy<=1.9.1,>=1.0.0; sys_platform == "win32" and python_version < "3.10"
Requires-Dist: scipy>=1.0.0; sys_platform != "win32" and python_version < "3.11"
Requires-Dist: scipy>=1.0.0; sys_platform == "win32" and python_version >= "3.10"
Requires-Dist: cloudpickle>=1.5.0
Requires-Dist: psutil>=5.9.0
Requires-Dist: tblib>=1.7.0
Requires-Dist: uvloop>=0.14.0; sys_platform != "win32"
Requires-Dist: packaging
Requires-Dist: click
Provides-Extra: dev
Requires-Dist: cython>=0.29; extra == "dev"
Requires-Dist: pytest>=3.5.0; extra == "dev"
Requires-Dist: pytest-cov>=2.5.0; extra == "dev"
Requires-Dist: pytest-timeout>=1.2.0; extra == "dev"
Requires-Dist: pytest-forked>=1.0; extra == "dev"
Requires-Dist: pytest-asyncio>=0.14.0; extra == "dev"
Requires-Dist: ipython>=6.5.0; extra == "dev"
Requires-Dist: sphinx; extra == "dev"
Requires-Dist: pydata-sphinx-theme>=0.3.0; extra == "dev"
Requires-Dist: sphinx-intl>=0.9.9; extra == "dev"
Requires-Dist: flake8>=3.8.0; extra == "dev"
Requires-Dist: black; extra == "dev"
Requires-Dist: uv; extra == "dev"
Requires-Dist: click; extra == "dev"
Provides-Extra: doc
Requires-Dist: ipython>=6.5.0; extra == "doc"
Requires-Dist: sphinx; extra == "doc"
Requires-Dist: pydata-sphinx-theme>=0.3.0; extra == "doc"
Requires-Dist: sphinx-intl>=0.9.9; extra == "doc"
Provides-Extra: extra
Requires-Dist: pyarrow>=5.0.0; extra == "extra"
Requires-Dist: torch; extra == "extra"
Provides-Extra: kubernetes
Requires-Dist: kubernetes>=10.0.0; extra == "kubernetes"
Provides-Extra: ray
Requires-Dist: xoscar_ray>=0.0.1; extra == "ray"
Dynamic: description
Dynamic: description-content-type
